[{"state":"Rajasthan","stateCode":"RJ","population":68621012,"populationDensity":201.0,"totalArea":342239.0},{"state":"Madhya Pradesh","stateCode":"MP","population":72597565,"populationDensity":236.0,"totalArea":308245.0},{"state":"Maharashtra","stateCode":"MH","population":112372972,"populationDensity":365.0,"totalArea":307713.0},{"state":"Uttar Pradesh","stateCode":"UP","population":199812341,"populationDensity":828.0,"totalArea":240928.0},{"state":"Jammu and Kashmir","stateCode":"JK","population":12548926,"populationDensity":57.0,"totalArea":222236.0},{"state":"Gujarat","stateCode":"GJ","population":60383628,"populationDensity":308.0,"totalArea":196024.0},{"state":"Karnataka","stateCode":"KA","population":61130704,"populationDensity":319.0,"totalArea":191791.0},{"state":"Andhra Pradesh","stateCode":"AP","population":49386799,"populationDensity":303.0,"totalArea":162968.0},{"state":"Odisha","stateCode":"OR","population":41947358,"populationDensity":269.0,"totalArea":155707.0},{"state":"Chattisgarh","stateCode":"CT","population":25540196,"populationDensity":189.0,"totalArea":135191.0},{"state":"Tamil Nadu","stateCode":"TN","population":72138958,"populationDensity":555.0,"totalArea":130058.0},{"state":"Telangana","stateCode":"TS","population":35286757,"populationDensity":307.0,"totalArea":114840.0},{"state":"Bihar","stateCode":"BH","population":103804637,"populationDensity":1102.0,"totalArea":94163.0},{"state":"West Bengal","stateCode":"WB","population":91347736,"populationDensity":1029.0,"totalArea":88752.0},{"state":"Jharkhand","stateCode":"JH","population":32966238,"populationDensity":414.0,"totalArea":79714.0},{"state":"Assam","stateCode":"AS","population":31169272,"populationDensity":397.0,"totalArea":78438.0},{"state":"Himachal Pradesh","stateCode":"HP","population":6864602,"populationDensity":123.0,"totalArea":55673.0},{"state":"Uttarakhand","stateCode":"UT","population":10116752,"populationDensity":189.0,"totalArea":53483.0},{"state":"Punjab","stateCode":"PB","population":27704236,"populationDensity":550.0,"totalArea":50362.0},{"state":"Haryana","stateCode":"HR","population":25353081,"populationDensity":573.0,"totalArea":44212.0},{"state":"Kerala","stateCode":"KL","population":33387677,"populationDensity":859.0,"totalArea":38863.0},{"state":"Meghalaya","stateCode":"ME","population":2964007,"populationDensity":132.0,"totalArea":22429.0},{"state":"Manipur","stateCode":"MN","population":2721756,"populationDensity":122.0,"totalArea":22327.0},{"state":"Mizoram","stateCode":"MI","population":1091014,"populationDensity":52.0,"totalArea":21081.0},{"state":"Arunachal Pradesh","stateCode":"AR","population":1382611,"populationDensity":50.0,"totalArea":21000.0},{"state":"Nagaland","stateCode":"NL","population":1980602,"populationDensity":119.0,"totalArea":16579.0},{"state":"Tripura","stateCode":"TR","population":3671032,"populationDensity":350.0,"totalArea":10486.0},{"state":"Sikkim","stateCode":"SK","population":607688,"populationDensity":86.0,"totalArea":7096.0},{"state":"Goa","stateCode":"GA","population":1457723,"populationDensity":394.0,"totalArea":3702.0}]